bernina_analysis/__init__.py
bernina_analysis-0.0.1.dist-info/METADATA
bernina_analysis-0.0.1.dist-info/WHEEL
bernina_analysis-0.0.1.dist-info/top_level.txt
bernina_analysis-0.0.1.dist-info/RECORD
